dhcpdoctor/__init__.py
dhcpdoctor/dhcpdoctor.py
dhcpdoctor/settings.py
dhcpdoctor-1.0.0.dist-info/entry_points.txt
dhcpdoctor-1.0.0.dist-info/LICENSE
dhcpdoctor-1.0.0.dist-info/WHEEL
dhcpdoctor-1.0.0.dist-info/METADATA
dhcpdoctor-1.0.0.dist-info/RECORD
